{
  "credit": "Made with Blockbench",
  "parent": "block/thin_block",
  "texture_size": [32, 32],
  "textures": {
    "3": "archmagica:blocks/fallen_adventurer1",
    "particle": "archmagica:blocks/fallen_adventurer1"
  },
  "elements": [
    {
      "from": [15.45, 0, 3.475],
      "to": [16.8, 1.625, 10.9],
      "rotation": {"angle": -22.5, "axis": "y", "origin": [15.8, 0, 9.9]},
      "faces": {
        "north": {"uv": [10, 9, 10.75, 9.75], "texture": "#3"},
        "east": {"uv": [7, 7.5, 10.75, 8.25], "texture": "#3"},
        "south": {"uv": [11.5, 12, 12.25, 12.75], "texture": "#3"},
        "west": {"uv": [8, 0, 11.75, 0.75], "texture": "#3"},
        "up": {"uv": [8.75, 4.75, 8, 1], "texture": "#3"},
        "down": {"uv": [7.75, 8.5, 7, 12.25], "texture": "#3"}
      }
    },
    {
      "from": [4, 3, 9],
      "to": [6, 4, 10],
      "rotation": {"angle": 0, "axis": "y", "origin": [8, 8, 8]},
      "faces": {
        "north": {"uv": [5, 13, 6, 13.5], "texture": "#3"},
        "east": {"uv": [13, 8, 13.5, 8.5], "texture": "#3"},
        "south": {"uv": [6, 13, 7, 13.5], "texture": "#3"},
        "west": {"uv": [13, 8.5, 13.5, 9], "texture": "#3"},
        "up": {"uv": [8, 13.5, 7, 13], "texture": "#3"},
        "down": {"uv": [9, 13, 8, 13.5], "texture": "#3"}
      }
    },
    {
      "from": [3.9, 0, 18.8],
      "to": [11.7, 6.95, 26],
      "rotation": {"angle": 45, "axis": "x", "origin": [11.2, 1.8, 21.6]},
      "faces": {
        "north": {"uv": [0, 0, 4, 3.5], "texture": "#3"},
        "east": {"uv": [0, 7, 3.5, 10.5], "texture": "#3"},
        "south": {"uv": [0, 3.5, 4, 7], "texture": "#3"},
        "west": {"uv": [3.5, 7.5, 7, 11], "texture": "#3"},
        "up": {"uv": [8, 7.5, 4, 4], "texture": "#3"},
        "down": {"uv": [8, 0, 4, 3.5], "texture": "#3"}
      }
    },
    {
      "from": [5, 4, 6],
      "to": [7, 5, 7],
      "rotation": {"angle": 0, "axis": "y", "origin": [8, 8, 8]},
      "faces": {
        "north": {"uv": [8, 12.5, 9, 13], "texture": "#3"},
        "east": {"uv": [13, 7, 13.5, 7.5], "texture": "#3"},
        "south": {"uv": [12.5, 12.5, 13.5, 13], "texture": "#3"},
        "west": {"uv": [13, 7.5, 13.5, 8], "texture": "#3"},
        "up": {"uv": [13.5, 12.5, 12.5, 12], "texture": "#3"},
        "down": {"uv": [5, 13, 4, 13.5], "texture": "#3"}
      }
    },
    {
      "from": [5.254, 5.7, 12.45],
      "to": [8.674, 6.84, 13.59],
      "rotation": {"angle": 0, "axis": "y", "origin": [8.674, 9.12, 18.15]},
      "faces": {
        "north": {"uv": [4, 3.5, 5.75, 4], "texture": "#3"},
        "east": {"uv": [13, 10, 13.5, 10.5], "texture": "#3"},
        "south": {"uv": [6, 3.5, 7.75, 4], "texture": "#3"},
        "west": {"uv": [13, 10.5, 13.5, 11], "texture": "#3"},
        "up": {"uv": [10.75, 9, 9, 8.5], "texture": "#3"},
        "down": {"uv": [13.25, 11.5, 11.5, 12], "texture": "#3"}
      }
    },
    {
      "from": [8.674, 5.7, 13.59],
      "to": [12.094, 6.84, 14.73],
      "rotation": {"angle": 0, "axis": "y", "origin": [8.674, 9.12, 18.15]},
      "faces": {
        "north": {"uv": [11.5, 1, 13.25, 1.5], "texture": "#3"},
        "east": {"uv": [13, 11, 13.5, 11.5], "texture": "#3"},
        "south": {"uv": [11.5, 1.5, 13.25, 2], "texture": "#3"},
        "west": {"uv": [0, 13.5, 0.5, 14], "texture": "#3"},
        "up": {"uv": [13.25, 2.5, 11.5, 2], "texture": "#3"},
        "down": {"uv": [13.25, 2.5, 11.5, 3], "texture": "#3"}
      }
    },
    {
      "from": [5, 5, 3],
      "to": [8, 6, 4],
      "rotation": {"angle": 0, "axis": "y", "origin": [8, 8, 8]},
      "faces": {
        "north": {"uv": [11.5, 9.5, 13, 10], "texture": "#3"},
        "east": {"uv": [13, 6, 13.5, 6.5], "texture": "#3"},
        "south": {"uv": [11.5, 10, 13, 10.5], "texture": "#3"},
        "west": {"uv": [13, 6.5, 13.5, 7], "texture": "#3"},
        "up": {"uv": [13, 11, 11.5, 10.5], "texture": "#3"},
        "down": {"uv": [13, 11, 11.5, 11.5], "texture": "#3"}
      }
    },
    {
      "from": [8, 5, 4],
      "to": [11, 6, 5],
      "rotation": {"angle": 0, "axis": "y", "origin": [8, 8, 8]},
      "faces": {
        "north": {"uv": [11.5, 7.5, 13, 8], "texture": "#3"},
        "east": {"uv": [13, 5, 13.5, 5.5], "texture": "#3"},
        "south": {"uv": [11.5, 8, 13, 8.5], "texture": "#3"},
        "west": {"uv": [13, 5.5, 13.5, 6], "texture": "#3"},
        "up": {"uv": [13, 9, 11.5, 8.5], "texture": "#3"},
        "down": {"uv": [13, 9, 11.5, 9.5], "texture": "#3"}
      }
    },
    {
      "from": [9, 4, 7],
      "to": [11, 5, 8],
      "rotation": {"angle": 0, "axis": "y", "origin": [8, 8, 8]},
      "faces": {
        "north": {"uv": [12, 6, 13, 6.5], "texture": "#3"},
        "east": {"uv": [13, 4, 13.5, 4.5], "texture": "#3"},
        "south": {"uv": [12, 6.5, 13, 7], "texture": "#3"},
        "west": {"uv": [13, 4.5, 13.5, 5], "texture": "#3"},
        "up": {"uv": [13, 7.5, 12, 7], "texture": "#3"},
        "down": {"uv": [8, 12.5, 7, 13], "texture": "#3"}
      }
    },
    {
      "from": [9, 4, 9],
      "to": [11, 5, 10],
      "rotation": {"angle": 0, "axis": "y", "origin": [8, 8, 8]},
      "faces": {
        "north": {"uv": [12, 4, 13, 4.5], "texture": "#3"},
        "east": {"uv": [13, 3, 13.5, 3.5], "texture": "#3"},
        "south": {"uv": [12, 4.5, 13, 5], "texture": "#3"},
        "west": {"uv": [13, 3.5, 13.5, 4], "texture": "#3"},
        "up": {"uv": [13, 5.5, 12, 5], "texture": "#3"},
        "down": {"uv": [13, 5.5, 12, 6], "texture": "#3"}
      }
    },
    {
      "from": [-1.5, 0, 10.3],
      "to": [-0.175, 7.625, 11.9],
      "rotation": {"angle": 0, "axis": "y", "origin": [3.5, 8, 9.3]},
      "faces": {
        "north": {"uv": [8, 8.5, 8.75, 12.25], "texture": "#3"},
        "east": {"uv": [9, 9, 9.75, 12.75], "texture": "#3"},
        "south": {"uv": [9, 1, 9.75, 4.75], "texture": "#3"},
        "west": {"uv": [10, 10, 10.75, 13.75], "texture": "#3"},
        "up": {"uv": [12.75, 0.75, 12, 0], "texture": "#3"},
        "down": {"uv": [12.75, 3, 12, 3.75], "texture": "#3"}
      }
    },
    {
      "from": [3, 0, 9],
      "to": [4, 3, 10],
      "rotation": {"angle": 0, "axis": "y", "origin": [8, 8, 8]},
      "faces": {
        "north": {"uv": [10.5, 6, 11, 7.5], "texture": "#3"},
        "east": {"uv": [11.5, 3, 12, 4.5], "texture": "#3"},
        "south": {"uv": [11.5, 4.5, 12, 6], "texture": "#3"},
        "west": {"uv": [11.5, 6, 12, 7.5], "texture": "#3"},
        "up": {"uv": [13.5, 0.5, 13, 0], "texture": "#3"},
        "down": {"uv": [13.5, 0.5, 13, 1], "texture": "#3"}
      }
    },
    {
      "from": [4, 0, 6],
      "to": [5, 4, 7],
      "rotation": {"angle": 0, "axis": "y", "origin": [8, 8, 8]},
      "faces": {
        "north": {"uv": [11, 3, 11.5, 5], "texture": "#3"},
        "east": {"uv": [11, 5, 11.5, 7], "texture": "#3"},
        "south": {"uv": [11, 7, 11.5, 9], "texture": "#3"},
        "west": {"uv": [11, 9, 11.5, 11], "texture": "#3"},
        "up": {"uv": [13, 13.5, 12.5, 13], "texture": "#3"},
        "down": {"uv": [13.5, 13, 13, 13.5], "texture": "#3"}
      }
    },
    {
      "from": [4.114, 0, 12.45],
      "to": [5.254, 5.7, 13.59],
      "rotation": {"angle": 0, "axis": "y", "origin": [8.674, 9.12, 18.15]},
      "faces": {
        "north": {"uv": [10, 1, 10.5, 3.75], "texture": "#3"},
        "east": {"uv": [10, 4, 10.5, 6.75], "texture": "#3"},
        "south": {"uv": [0, 10.5, 0.5, 13.25], "texture": "#3"},
        "west": {"uv": [0.5, 10.5, 1, 13.25], "texture": "#3"},
        "up": {"uv": [13.5, 9.5, 13, 9], "texture": "#3"},
        "down": {"uv": [13.5, 9.5, 13, 10], "texture": "#3"}
      }
    },
    {
      "from": [4, 0, 3],
      "to": [5, 5, 4],
      "rotation": {"angle": 0, "axis": "y", "origin": [8, 8, 8]},
      "faces": {
        "north": {"uv": [3, 10.5, 3.5, 13], "texture": "#3"},
        "east": {"uv": [10.5, 1, 11, 3.5], "texture": "#3"},
        "south": {"uv": [10.5, 3.5, 11, 6], "texture": "#3"},
        "west": {"uv": [3.5, 11, 4, 13.5], "texture": "#3"},
        "up": {"uv": [12, 13.5, 11.5, 13], "texture": "#3"},
        "down": {"uv": [12.5, 13, 12, 13.5], "texture": "#3"}
      }
    },
    {
      "from": [11, 0, 9],
      "to": [12, 4, 10],
      "rotation": {"angle": 0, "axis": "y", "origin": [8, 8, 8]},
      "faces": {
        "north": {"uv": [6, 11, 6.5, 13], "texture": "#3"},
        "east": {"uv": [6.5, 11, 7, 13], "texture": "#3"},
        "south": {"uv": [11, 11, 11.5, 13], "texture": "#3"},
        "west": {"uv": [11, 1, 11.5, 3], "texture": "#3"},
        "up": {"uv": [10, 13.5, 9.5, 13], "texture": "#3"},
        "down": {"uv": [11.5, 13, 11, 13.5], "texture": "#3"}
      }
    },
    {
      "from": [12.094, 0, 13.59],
      "to": [13.234, 5.7, 14.73],
      "rotation": {"angle": 0, "axis": "y", "origin": [8.674, 9.12, 18.15]},
      "faces": {
        "north": {"uv": [1, 10.5, 1.5, 13.25], "texture": "#3"},
        "east": {"uv": [1.5, 10.5, 2, 13.25], "texture": "#3"},
        "south": {"uv": [2, 10.5, 2.5, 13.25], "texture": "#3"},
        "west": {"uv": [2.5, 10.5, 3, 13.25], "texture": "#3"},
        "up": {"uv": [1, 14, 0.5, 13.5], "texture": "#3"},
        "down": {"uv": [1.5, 13.5, 1, 14], "texture": "#3"}
      }
    },
    {
      "from": [11, 0, 7],
      "to": [12, 4, 8],
      "rotation": {"angle": 0, "axis": "y", "origin": [8, 8, 8]},
      "faces": {
        "north": {"uv": [4, 11, 4.5, 13], "texture": "#3"},
        "east": {"uv": [4.5, 11, 5, 13], "texture": "#3"},
        "south": {"uv": [5, 11, 5.5, 13], "texture": "#3"},
        "west": {"uv": [5.5, 11, 6, 13], "texture": "#3"},
        "up": {"uv": [3.5, 13.5, 3, 13], "texture": "#3"},
        "down": {"uv": [9.5, 13, 9, 13.5], "texture": "#3"}
      }
    },
    {
      "from": [11, 0, 4],
      "to": [12, 5, 5],
      "rotation": {"angle": 0, "axis": "y", "origin": [8, 8, 8]},
      "faces": {
        "north": {"uv": [8, 5, 8.5, 7.5], "texture": "#3"},
        "east": {"uv": [8.5, 5, 9, 7.5], "texture": "#3"},
        "south": {"uv": [9, 5, 9.5, 7.5], "texture": "#3"},
        "west": {"uv": [9.5, 5, 10, 7.5], "texture": "#3"},
        "up": {"uv": [4, 7.5, 3.5, 7], "texture": "#3"},
        "down": {"uv": [10.5, 7, 10, 7.5], "texture": "#3"}
      }
    }
  ],
  "display": {
    "thirdperson_righthand": {
      "rotation": [88.5, 0, 0],
      "scale": [0.31, 0.31, 0.31]
    },
    "thirdperson_lefthand": {
      "rotation": [88.5, 0, 0],
      "scale": [0.31, 0.31, 0.31]
    },
    "firstperson_righthand": {
      "translation": [0, 5.25, 0]
    },
    "firstperson_lefthand": {
      "translation": [0, 5.25, 0]
    },
    "ground": {
      "translation": [0, 5, 0]
    },
    "gui": {
      "rotation": [17, 142, 0],
      "translation": [-1.25, 2.5, 0],
      "scale": [0.58008, 0.58008, 0.58008]
    },
    "fixed": {
      "rotation": [-59.75, 0, 0],
      "translation": [0, 0, -6]
    }
  },
  "groups": [
    {
      "name": "VoxelShapes",
      "origin": [8, 8, 8],
      "color": 0,
      "children": [0, 1, 2, 3, 4, 5, 6, 7, 8, 9, 10, 11, 12, 13, 14, 15, 16, 17, 18]
    }
  ]
}